ansible_risk_insight/__init__.py
ansible_risk_insight/_version.py
ansible_risk_insight/analyzer.py
ansible_risk_insight/ansible_builtin_modules.json
ansible_risk_insight/ansible_variables.txt
ansible_risk_insight/awx_utils.py
ansible_risk_insight/batch.sh
ansible_risk_insight/builtin-modules.txt
ansible_risk_insight/context.py
ansible_risk_insight/dependency_dir_preparator.py
ansible_risk_insight/dependency_finder.py
ansible_risk_insight/finder.py
ansible_risk_insight/findings.py
ansible_risk_insight/key_test.py
ansible_risk_insight/keyutil.py
ansible_risk_insight/loader.py
ansible_risk_insight/logger.py
ansible_risk_insight/model_loader.py
ansible_risk_insight/models.py
ansible_risk_insight/parser.py
ansible_risk_insight/ram_generator.py
ansible_risk_insight/requirements.txt
ansible_risk_insight/risk_assessment_model.py
ansible_risk_insight/risk_detector.py
ansible_risk_insight/safe_glob.py
ansible_risk_insight/scanner.py
ansible_risk_insight/task_keywords.txt
ansible_risk_insight/tree.py
ansible_risk_insight/utils.py
ansible_risk_insight/yaml.py
ansible_risk_insight/yaml_utils.py
ansible_risk_insight/annotators/__init__.py
ansible_risk_insight/annotators/annotator_base.py
ansible_risk_insight/annotators/ansible_builtin.py
ansible_risk_insight/annotators/ansible_builtin.py.bak
ansible_risk_insight/annotators/module_annotator_base.py
ansible_risk_insight/annotators/risk_annotator_base.py
ansible_risk_insight/annotators/sample_custom_annotator.py
ansible_risk_insight/annotators/variable_resolver.py
ansible_risk_insight/annotators/ansible.builtin/apt.py
ansible_risk_insight/annotators/ansible.builtin/apt_key.py
ansible_risk_insight/annotators/ansible.builtin/assemble.py
ansible_risk_insight/annotators/ansible.builtin/blockinfile.py
ansible_risk_insight/annotators/ansible.builtin/command.py
ansible_risk_insight/annotators/ansible.builtin/dnf.py
ansible_risk_insight/annotators/ansible.builtin/expect.py
ansible_risk_insight/annotators/ansible.builtin/file.py
ansible_risk_insight-0.2.10.dist-info/LICENSE
ansible_risk_insight-0.2.10.dist-info/METADATA
ansible_risk_insight-0.2.10.dist-info/WHEEL
ansible_risk_insight-0.2.10.dist-info/entry_points.txt
ansible_risk_insight-0.2.10.dist-info/top_level.txt
ansible_risk_insight-0.2.10.dist-info/RECORD
