Metadata-Version: 2.1
Name: ansible-risk-insight
Version: 0.2.10
Summary: My package description
License: Apache License 2.0
Keywords: one,two
Classifier: Programming Language :: Python :: 3
Requires-Python: >=3.7
License-File: LICENSE
Requires-Dist: gitdb
Requires-Dist: joblib
Requires-Dist: jsonpickle
Requires-Dist: PyYAML
Requires-Dist: smmap
Requires-Dist: tabulate
Requires-Dist: requests
Requires-Dist: ruamel.yaml
Requires-Dist: filelock
Requires-Dist: rapidfuzz
